canns/__init__.py
canns/_version.py
canns/py.typed
canns/analyzer/__init__.py
canns/analyzer/data/__init__.py
canns/analyzer/data/asa/__init__.py
canns/analyzer/data/asa/coho.py
canns/analyzer/data/asa/cohomap.py
canns/analyzer/data/asa/cohomap_vectors.py
canns/analyzer/data/asa/cohospace.py
canns/analyzer/data/asa/cohospace_phase_centers.py
canns/analyzer/data/asa/cohospace_scatter.py
canns/analyzer/data/asa/config.py
canns/analyzer/data/asa/decode.py
canns/analyzer/data/asa/embedding.py
canns/analyzer/data/asa/fly_roi.py
canns/analyzer/data/asa/fr.py
canns/analyzer/data/asa/path.py
canns/analyzer/data/asa/plotting.py
canns/analyzer/data/asa/tda.py
canns/analyzer/data/asa/utils.py
canns/analyzer/data/cell_classification/__init__.py
canns/analyzer/data/cell_classification/core/__init__.py
canns/analyzer/data/cell_classification/core/btn.py
canns/analyzer/data/cell_classification/core/grid_cells.py
canns/analyzer/data/cell_classification/core/grid_modules_leiden.py
canns/analyzer/data/cell_classification/core/head_direction.py
canns/analyzer/data/cell_classification/core/spatial_analysis.py
canns/analyzer/data/cell_classification/io/__init__.py
canns/analyzer/data/cell_classification/io/matlab_loader.py
canns/analyzer/data/cell_classification/utils/__init__.py
canns/analyzer/data/cell_classification/utils/circular_stats.py
canns/analyzer/data/cell_classification/utils/correlation.py
canns/analyzer/data/cell_classification/utils/geometry.py
canns/analyzer/data/cell_classification/utils/image_processing.py
canns/analyzer/data/cell_classification/visualization/__init__.py
canns/analyzer/data/cell_classification/visualization/btn_plots.py
canns/analyzer/data/cell_classification/visualization/grid_plots.py
canns/analyzer/data/cell_classification/visualization/hd_plots.py
canns/analyzer/metrics/__init__.py
canns/analyzer/metrics/spatial_metrics.py
canns/analyzer/metrics/systematic_ratemap.py
canns/analyzer/metrics/utils.py
canns/analyzer/model_specific/__init__.py
canns-0.15.1.dist-info/METADATA
canns-0.15.1.dist-info/WHEEL
canns-0.15.1.dist-info/entry_points.txt
canns-0.15.1.dist-info/licenses/LICENSE
canns-0.15.1.dist-info/RECORD
