Metadata-Version: 2.4
Name: canns
Version: 0.15.1
Summary: A Python Library for Continuous Attractor Neural Networks
Project-URL: Repository, https://github.com/routhleck/canns
Author-email: Sichao He <sichaohe@outlook.com>
License-Expression: Apache-2.0
License-File: LICENSE
Classifier: Development Status :: 4 - Beta
Classifier: Intended Audience :: Developers
Classifier: Operating System :: OS Independent
Classifier: Programming Language :: Python
Classifier: Programming Language :: Python :: 3
Classifier: Programming Language :: Python :: 3.11
Classifier: Programming Language :: Python :: 3.12
Classifier: Programming Language :: Python :: 3.13
Classifier: Typing :: Typed
Requires-Python: <4.0,>=3.11
Requires-Dist: brainpy[cpu]
Requires-Dist: canns-lib>=0.6.2
Requires-Dist: climage>=0.2.2
Requires-Dist: furo>=2025.7.19
Requires-Dist: h5py>=3.7
Requires-Dist: igraph>=1.0.0
Requires-Dist: imageio[ffmpeg]>=2.37.0
Requires-Dist: leidenalg>=0.11.0
Requires-Dist: matplotlib>=3.5
Requires-Dist: notebook>=7.4.4
Requires-Dist: numba>=0.56.0
Requires-Dist: numpy<2.3,>=1.24
Requires-Dist: scikit-image>=0.19
Requires-Dist: scipy>=1.9.0
Requires-Dist: seaborn>=0.13.2
Requires-Dist: textual>=7.3.0
Requires-Dist: tqdm
Provides-Extra: cpu
Requires-Dist: brainpy[cpu]; extra == 'cpu'
Provides-Extra: cuda12
Requires-Dist: brainpy[cuda12]; (platform_system == 'Linux') and extra == 'cuda12'
Provides-Extra: cuda13
Requires-Dist: brainpy[cuda13]; (platform_system == 'Linux') and extra == 'cuda13'
Provides-Extra: gui
Requires-Dist: imageio; extra == 'gui'
Requires-Dist: pillow; extra == 'gui'
Requires-Dist: pyside6>=6.6.0; extra == 'gui'
Requires-Dist: qtawesome; extra == 'gui'
Requires-Dist: requests>=2.31.0; extra == 'gui'
Provides-Extra: tpu
Requires-Dist: brainpy[tpu]; (platform_system == 'Linux') and extra == 'tpu'
